spark_df_profiling_optimus/__init__.py
spark_df_profiling_optimus/base.py
spark_df_profiling_optimus/formatters.py
spark_df_profiling_optimus/spark_df_profiling_optimus.mplstyle
spark_df_profiling_optimus/templates.py
spark_df_profiling_optimus/tests.py.old.py
spark_df_profiling_optimus/templates/_row_footer.html
spark_df_profiling_optimus/templates/_row_header.html
spark_df_profiling_optimus/templates/_row_header_ignore.html
spark_df_profiling_optimus/templates/base.html
spark_df_profiling_optimus/templates/freq_table.html
spark_df_profiling_optimus/templates/freq_table_row.html
spark_df_profiling_optimus/templates/mini_freq_table.html
spark_df_profiling_optimus/templates/mini_freq_table_row.html
spark_df_profiling_optimus/templates/overview.html
spark_df_profiling_optimus/templates/row_cat.html
spark_df_profiling_optimus/templates/row_const.html
spark_df_profiling_optimus/templates/row_corr.html
spark_df_profiling_optimus/templates/row_date.html
spark_df_profiling_optimus/templates/row_num.html
spark_df_profiling_optimus/templates/row_unique.html
spark_df_profiling_optimus/templates/sample.html
spark_df_profiling_optimus/templates/wrapper.html
spark_df_profiling_optimus/templates/wrapper_static.html
spark_df_profiling_optimus/templates/css/bootstrap-theme.min.css
spark_df_profiling_optimus/templates/css/bootstrap.min.css
spark_df_profiling_optimus/templates/js/bootstrap.min.js
spark_df_profiling_optimus/templates/js/jquery.min.js
spark_df_profiling_optimus-0.1.1.dist-info/DESCRIPTION.rst
spark_df_profiling_optimus-0.1.1.dist-info/METADATA
spark_df_profiling_optimus-0.1.1.dist-info/RECORD
spark_df_profiling_optimus-0.1.1.dist-info/WHEEL
spark_df_profiling_optimus-0.1.1.dist-info/metadata.json
spark_df_profiling_optimus-0.1.1.dist-info/top_level.txt
